        
{ 
    "tableData":        
        [
            {
                "name": "Rebecca Bauch",
                "company": "Daugherty-Daniel",
                "city": "South Cory",
                "progress": {
                    "max": 100,
                    "value": 79
                },
                "created": "Oct 25, 2021",
                "image": "https://avatars.dicebear.com/v2/initials/rebecca-bauch.svg"
            },

            {
                "name": "Felicita Yundt",
                "company": "Johns-Weissnat",
                "city": "East Ariel",
                "progress": {
                    "max": 100,
                    "value": 67
                },
                "created": "Jan 8, 2021",
                "image": "https://avatars.dicebear.com/v2/initials/felicita-yundt.svg"
            },

            {
                "name": "Mr. Larry Satterfield V",
                "company": "Hyatt Ltd",
                "city": "Windlerburgh",
                "progress": {
                    "max": 100,
                    "value": 16
                },
                "created": "Dec 18, 2021",
                "image": "https://avatars.dicebear.com/v2/initials/mr-larry-satterfield-v.svg"
            },

            {
                "name": "Mr. Broderick Kub",
                "company": "Kshlerin, Bauch and Ernser",
                "city": "New Kirstenport",
                "progress": {
                    "max": 100,
                    "value": 71
                },
                "created": "Sep 13, 2021",
                "image": "https://avatars.dicebear.com/v2/initials/mr-broderick-kub.svg"
            },

            {
                "name": "Barry Weber",
                "company": "Schulist, Mosciski and Heidenreich",
                "city": "East Violettestad",
                "progress": {
                    "max": 100,
                    "value": 80
                },
                "created": "Jul 24, 2021",
                "image": "https://avatars.dicebear.com/v2/initials/barry-weber.svg"
            },


            {
                "name": "Bert Kautzer MD",
                "company": "Gerhold and Sons",
                "city": "Mayeport",
                "progress": {
                    "max": 100,
                    "value": 62
                },
                "created": "Mar 30, 2021",
                "image": "https://avatars.dicebear.com/v2/initials/bert-kautzer-md.svg"
            },

            {
                "name": "Lonzo Steuber",
                "company": "Skiles Ltd",
                "city": "Marilouville",
                "progress": {
                    "max": 100,
                    "value": 17
                },
                "created": "Feb 12, 2021",
                "image": "https://avatars.dicebear.com/v2/initials/lonzo-steuber.svg"
            },

            {
                "name": "Jonathon Hahn",
                "company": "Flatley Ltd",
                "city": "Billiemouth",
                "progress": {
                    "max": 100,
                    "value": 74
                },
                "created": "Dec 30, 2021",
                "image": "https://avatars.dicebear.com/v2/initials/jonathon-hahn.svg"
            },

            {
                "name": "Ryley Wuckert",
                "company": "Heller-Little",
                "city": "Emeraldtown",
                "progress": {
                    "max": 100,
                    "value": 54
                },
                "created": "Jun 28, 2021",
                "image": "https://avatars.dicebear.com/v2/initials/ryley-wuckert.svg"
            },

            {
                "name": "Sienna Hayes",
                "company": "Conn, Jerde and Douglas",
                "city": "Jonathanfort",
                "progress": {
                    "max": 100,
                    "value": 55
                },
                "created": "Mar 7, 2021",
                "image": "https://avatars.dicebear.com/v2/initials/sienna-hayes.svg"
            }
        ]
    }